{
    "data": [
      {
        "instrucid": "11211",
        "instrucname": "Limotan, Kyle Vincent",
        "schoolyear": 2021,
        "semester": "1st",
        "publish": "Year",
        "report": "Yes"
      },
      {
        "instrucid": "11111",
        "instrucname": "Limotan, Kyle Vincent",
        "schoolyear": 2020,
        "semester": "summer",
        "publish": "Year",
        "report": "Yes"
      },  {
        "instrucid": "11151",
        "instrucname": "Limotan, Maria Vincent",
        "schoolyear": 2021,
        "semester": "1st",
        "publish": "Year",
        "report": "Yes"
      },  {
        "instrucid": "11611",
        "instrucname": "Limotan, St Vincent",
        "schoolyear": 2021,
        "semester": "1st",
        "publish": "Year",
        "report": "Yes"
      },  {
        "instrucid": "11131",
        "instrucname": "Limotan, asd Vincent",
        "schoolyear": 2021,
        "semester": "1st",
        "publish": "Year",
        "report": "Yes"
      }

    ]
  }